.coveragerc
LICENSE
MANIFEST.in
README.md
setup.py
./README.md
Finance_Ultron.egg-info/PKG-INFO
Finance_Ultron.egg-info/SOURCES.txt
Finance_Ultron.egg-info/dependency_links.txt
Finance_Ultron.egg-info/requires.txt
Finance_Ultron.egg-info/top_level.txt
demo/__init__.py
demo/ct.py
demo/daily_factor.py
demo/fut_strategy.py
demo/ga_factor.py
demo/grid_search.py
demo/machine.py
demo/op_factor.py
demo/op_model.py
demo/optimize.py
demo/risk_model.py
demo/sentry.py
demo/stk_strategy.py
demo/strategy.py
demo/support.py
demo/transformer.py
requirements/py2.txt
requirements/py3.txt
ultron/__init__.py
ultron/config.py
ultron/env.py
ultron/setting.py
ultron/test_suite.py
ultron/cluster/__init__.py
ultron/cluster/central/__init__.py
ultron/cluster/central/central_engine.py
ultron/cluster/central/extern_modules/__init__.py
ultron/cluster/central/extern_modules/base_module.py
ultron/cluster/central/extern_modules/modules_info.py
ultron/cluster/central/extern_modules/login/__init__.py
ultron/cluster/central/extern_modules/login/module.py
ultron/cluster/central/extern_modules/middleware/__init__.py
ultron/cluster/central/extern_modules/middleware/module.py
ultron/cluster/central/extern_modules/packet/__init__.py
ultron/cluster/central/extern_modules/packet/module.py
ultron/cluster/central/extern_modules/tasks/__init__.py
ultron/cluster/central/extern_modules/tasks/module.py
ultron/cluster/invoke/__init__.py
ultron/cluster/invoke/app_engine.py
ultron/cluster/invoke/cache_data.py
ultron/cluster/invoke/submit_tasks.py
ultron/cluster/work/__init__.py
ultron/cluster/work/work_engine.py
ultron/cluster/work/extern_modules/__init__.py
ultron/cluster/work/extern_modules/base_module.py
ultron/cluster/work/extern_modules/modules_info.py
ultron/cluster/work/extern_modules/login/__init__.py
ultron/cluster/work/extern_modules/login/module.py
ultron/cluster/work/extern_modules/packet/__init__.py
ultron/cluster/work/extern_modules/packet/module.py
ultron/cluster/work/extern_modules/tasks/__init__.py
ultron/cluster/work/extern_modules/tasks/module.py
ultron/factor/__init__.py
ultron/factor/impl.py
ultron/factor/utilities.py
ultron/factor/alphalens/__init__.py
