Metadata-Version: 2.1
Name: Finance-Ultron
Version: 1.3.3
Summary: By traders for AI.  FinUltron 1.3.3
Home-page: https://github.com/ChaosTransaction/notebook
Author: flaght
Author-email: flaght@gmail.com
License-File: LICENSE
